{
    "id": 130514121,
    "name": "10 000",
    "author": "fzxqoe",
    "creators": [],
    "verifier": "zis76",
    "verification": "https://youtu.be/14c3ypg66dU?si=0J2chgYNKbULzIIe",
    "percentToQualify": "100",
    "records": [
         {
            "user": "Tomato",
            "link": "https://discordapp.com/channels/1413625809112924307/1413628930065301616/1456536951816458313",
            "hz": "240",
            "percent": 100
        },
         {
            "user": "finni1505",
            "link": "https://medal.tv/de/games/geometry-dash/clips/lPZYAPmEgpltQ89ik?invite=cr-MSw3b3gsMzY5MjUzOTQw&v=30",
            "hz": "240",
            "percent": 100
        },
        {
            "user": "Nuridint3b",
            "link": "https://discord.com/channels/1413625809112924307/1413628930065301616/1457171696934195364",
            "hz": "60",
            "percent": 100,
            "mobile": "true"
        },
        {
            "user": "Rusty",
            "link": "https://www.youtube.com/watch?v=ojVElO6ouoo",
            "hz": "360",
            "percent": 100
        },
        {
            "user": "Sadisyourlife",
            "link": "https://discord.com/channels/1413625809112924307/1413628930065301616/1460715382070317387",
            "hz": "240",
            "percent": 100
        },
        {
            "user": "aelz",
            "link": "https://www.youtube.com/live/4QU4yfnmqYw",
            "hz": "240",
            "percent": 100
      },
        {
            "user": "fjkr",
            "link": "https://discord.com/channels/1413625809112924307/1413628930065301616/1469780350799712510",
            "hz": "CBF",
            "percent": 100
        }
    ]
}
