{
    "id": 131367900,
    "name": "BILBERT Z",
    "author": "idkthisnamelol",
    "creators": [],
    "verifier": "Bananas",
    "verification": "https://youtu.be/gaJdFu2cocU",
    "percentToQualify": "100",
    "fps": "Any",
    "records": [
        {
            "user": "tFluffy",
            "link": "https://discord.com/channels/1413625809112924307/1413628930065301616/1460977937896702067",
            "hz": "240",
            "percent": 100
        },
        {
            "user": "finni1505",
            "link": "https://medal.tv/games/geometry-dash/clips/lZBiJRlyxvjjO0gOW?invite=cr-MSxZNEcsMzY5MjUzOTQw",
            "hz": "CBF",
            "percent": 100
        }
    ]
}
